paketle/__init__.py
paketle/cli.py
paketle/paketle.py
paketle-0.1.0.dist-info/AUTHORS.rst
paketle-0.1.0.dist-info/LICENSE
paketle-0.1.0.dist-info/METADATA
paketle-0.1.0.dist-info/WHEEL
paketle-0.1.0.dist-info/entry_points.txt
paketle-0.1.0.dist-info/top_level.txt
paketle-0.1.0.dist-info/RECORD
