Metadata-Version: 2.1
Name: paketle
Version: 0.1.0
Summary: Basit bir paketleme denemesi
Home-page: https://github.com/pogrenen/paketle
Author: Ziya Efkar
Author-email: hpargh0than@gmail.com
License: MIT license
Keywords: paketle
Platform: UNKNOWN
Classifier: Development Status :: 2 - Pre-Alpha
Classifier: Intended Audience :: Developers
Classifier: License :: OSI Approved :: MIT License
Classifier: Natural Language :: English
Classifier: Programming Language :: Python :: 2
Classifier: Programming Language :: Python :: 2.7
Classifier: Programming Language :: Python :: 3
Classifier: Programming Language :: Python :: 3.4
Classifier: Programming Language :: Python :: 3.5
Classifier: Programming Language :: Python :: 3.6
Classifier: Programming Language :: Python :: 3.7
Requires-Dist: Click (>=6.0)
